Gourang/Gourang.py
Gourang/__init__.py
Gourang-1.0.0.dist-info/LICENSE.txt
Gourang-1.0.0.dist-info/METADATA
Gourang-1.0.0.dist-info/WHEEL
Gourang-1.0.0.dist-info/top_level.txt
Gourang-1.0.0.dist-info/RECORD
