Metadata-Version: 2.1
Name: Gourang
Version: 1.0.0
Summary: A simple Python package
Home-page: https://google.com
Author: Gourang Agrawal
Author-email: gourangagrawal843@gmail.com
Project-URL: Bug Tracker, https://google.com
Project-URL: repository, https://google.com
Classifier: Programming Language :: Python :: 3
Classifier: License :: OSI Approved :: MIT License
Classifier: Operating System :: OS Independent
Requires-Python: >=3.6
License-File: LICENSE.txt
